{
  "COMMS": [
    {
      "('HI8D', 'KF0AX')": [
        {
          "completed": false
        },
        {
          "turn": 1,
          "message": "KF0AX HI8D FK58",
          "translated_message": "HI8D sends a grid square location of FK58 to KF0AX.",
          "packet": {
            "snr": 5,
            "delta_time": 0.5,
            "frequency_offset": 763,
            "frequency": 14.074762999999999,
            "band": "20m",
            "message": "KF0AX HI8D FK58",
            "schema": 2,
            "program": "WSJT-X",
            "packet_type": 2
          },
          "type": "Grid Square Report"
        },
        {
          "turn": 2,
          "message": "KF0AX HI8D FK58",
          "translated_message": "HI8D sends a grid square location of FK58 to KF0AX.",
          "packet": {
            "snr": 3,
            "delta_time": 0.5,
            "frequency_offset": 762,
            "frequency": 14.074762,
            "band": "20m",
            "message": "KF0AX HI8D FK58",
            "schema": 2,
            "program": "WSJT-X",
            "packet_type": 2
          },
          "type": "Grid Square Report"
        },
        {
          "turn": 3,
          "message": "KF0AX HI8D FK58",
          "translated_message": "HI8D sends a grid square location of FK58 to KF0AX.",
          "packet": {
            "snr": 8,
            "delta_time": 0.5,
            "frequency_offset": 762,
            "frequency": 14.074762,
            "band": "20m",
            "message": "KF0AX HI8D FK58",
            "schema": 2,
            "program": "WSJT-X",
            "packet_type": 2
          },
          "type": "Grid Square Report"
        }
      ],
      "('KF0AX', 'KP4QVQ')": [
        {
          "completed": false
        },
        {
          "turn": 1,
          "message": "KF0AX KP4QVQ FK68",
          "translated_message": "KP4QVQ sends a grid square location of FK68 to KF0AX.",
          "packet": {
            "snr": -1,
            "delta_time": 0.4000000059604645,
            "frequency_offset": 438,
            "frequency": 14.074438,
            "band": "20m",
            "message": "KF0AX KP4QVQ FK68",
            "schema": 2,
            "program": "WSJT-X",
            "packet_type": 2
          },
          "type": "Grid Square Report"
        },
        {
          "turn": 2,
          "message": "KF0AX KP4QVQ FK68",
          "translated_message": "KP4QVQ sends a grid square location of FK68 to KF0AX.",
          "packet": {
            "snr": -3,
            "delta_time": 0.5,
            "frequency_offset": 438,
            "frequency": 14.074438,
            "band": "20m",
            "message": "KF0AX KP4QVQ FK68",
            "schema": 2,
            "program": "WSJT-X",
            "packet_type": 2
          },
          "type": "Grid Square Report"
        },
        {
          "turn": 3,
          "message": "KF0AX KP4QVQ FK68",
          "translated_message": "KP4QVQ sends a grid square location of FK68 to KF0AX.",
          "packet": {
            "snr": 2,
            "delta_time": 0.5,
            "frequency_offset": 437,
            "frequency": 14.074437,
            "band": "20m",
            "message": "KF0AX KP4QVQ FK68",
            "schema": 2,
            "program": "WSJT-X",
            "packet_type": 2
          },
          "type": "Grid Square Report"
        },
        {
          "turn": 4,
          "message": "KF0AX KP4QVQ FK68",
          "translated_message": "KP4QVQ sends a grid square location of FK68 to KF0AX.",
          "packet": {
            "snr": 2,
            "delta_time": 0.5,
            "frequency_offset": 437,
            "frequency": 14.074437,
            "band": "20m",
            "message": "KF0AX KP4QVQ FK68",
            "schema": 2,
            "program": "WSJT-X",
            "packet_type": 2
          },
          "type": "Grid Square Report"
        }
      ],
      "('CU6AB', 'KG4VUK')": [
        {
          "completed": false
        },
        {
          "turn": 1,
          "message": "CU6AB KG4VUK EM64",
          "translated_message": "KG4VUK sends a grid square location of EM64 to CU6AB.",
          "packet": {
            "snr": -16,
            "delta_time": 0.5,
            "frequency_offset": 1338,
            "frequency": 14.075338,
            "band": "20m",
            "message": "CU6AB KG4VUK EM64",
            "schema": 2,
            "program": "WSJT-X",
            "packet_type": 2
          },
          "type": "Grid Square Report"
        }
      ],
      "('W6PNH', 'W7RTA')": [
        {
          "completed": true
        },
        {
          "turn": 1,
          "message": "W7RTA W6PNH CM99",
          "translated_message": "W6PNH sends a grid square location of CM99 to W7RTA.",
          "packet": {
            "snr": -15,
            "delta_time": 0.5,
            "frequency_offset": 688,
            "frequency": 14.074688,
            "band": "20m",
            "message": "W7RTA W6PNH CM99",
            "schema": 2,
            "program": "WSJT-X",
            "packet_type": 2
          },
          "type": "Grid Square Report"
        },
        {
          "turn": 2,
          "message": "W7RTA W6PNH CM99",
          "translated_message": "W6PNH sends a grid square location of CM99 to W7RTA.",
          "packet": {
            "snr": -20,
            "delta_time": 0.5,
            "frequency_offset": 687,
            "frequency": 14.074686999999999,
            "band": "20m",
            "message": "W7RTA W6PNH CM99",
            "schema": 2,
            "program": "WSJT-X",
            "packet_type": 2
          },
          "type": "Grid Square Report"
        },
        {
          "turn": 3,
          "message": "W7RTA W6PNH R-01",
          "translated_message": "W6PNH says Roger and reports a signal report of -01 to W7RTA.",
          "packet": {
            "snr": -13,
            "delta_time": 0.5,
            "frequency_offset": 687,
            "frequency": 14.074686999999999,
            "band": "20m",
            "message": "W7RTA W6PNH R-01",
            "schema": 2,
            "program": "WSJT-X",
            "packet_type": 2
          },
          "type": "Signal Report"
        },
        {
          "turn": 4,
          "message": "W7RTA W6PNH 73",
          "translated_message": "W6PNH sends their well wishes to W7RTA, concluding the connection.",
          "packet": {
            "snr": -10,
            "delta_time": 0.5,
            "frequency_offset": 687,
            "frequency": 14.074686999999999,
            "band": "20m",
            "message": "W7RTA W6PNH 73",
            "schema": 2,
            "program": "WSJT-X",
            "packet_type": 2
          },
          "type": "Goodbye"
        }
      ],
      "('VA5KEN', 'WB3FBR')": [
        {
          "completed": true
        },
        {
          "turn": 1,
          "message": "WB3FBR VA5KEN RR73",
          "translated_message": "VA5KEN sends a Roger Roger to WB3FBR and says goodbye, concluding the connection.",
          "packet": {
            "snr": -15,
            "delta_time": 0.6000000238418579,
            "frequency_offset": 631,
            "frequency": 14.074631,
            "band": "20m",
            "message": "WB3FBR VA5KEN RR73",
            "schema": 2,
            "program": "WSJT-X",
            "packet_type": 2
          },
          "type": "RR & Goodbye"
        }
      ],
      "('AF0E', 'W7RTA')": [
        {
          "completed": true
        },
        {
          "turn": 1,
          "message": "W7RTA AF0E RR73",
          "translated_message": "AF0E sends a Roger Roger to W7RTA and says goodbye, concluding the connection.",
          "packet": {
            "snr": -6,
            "delta_time": 0.5,
            "frequency_offset": 1077,
            "frequency": 14.075077,
            "band": "20m",
            "message": "W7RTA AF0E RR73",
            "schema": 2,
            "program": "WSJT-X",
            "packet_type": 2
          },
          "type": "RR & Goodbye"
        }
      ],
      "('KF0AX', 'NO4D')": [
        {
          "completed": true
        },
        {
          "turn": 1,
          "message": "KF0AX NO4D 73",
          "translated_message": "NO4D sends their well wishes to KF0AX, concluding the connection.",
          "packet": {
            "snr": -16,
            "delta_time": 0.800000011920929,
            "frequency_offset": 848,
            "frequency": 14.074848,
            "band": "20m",
            "message": "KF0AX NO4D 73",
            "schema": 2,
            "program": "WSJT-X",
            "packet_type": 2
          },
          "type": "Goodbye"
        }
      ],
      "('JA0JWQ', 'LY2PPS')": [
        {
          "completed": false
        },
        {
          "turn": 1,
          "message": "LY2PPS JA0JWQ -15",
          "translated_message": "JA0JWQ sends signal report of -15 to LY2PPS.",
          "packet": {
            "snr": -21,
            "delta_time": 0.6000000238418579,
            "frequency_offset": 132,
            "frequency": 14.074132,
            "band": "20m",
            "message": "LY2PPS JA0JWQ -15",
            "schema": 2,
            "program": "WSJT-X",
            "packet_type": 2
          },
          "type": "Signal Report"
        }
      ],
      "('K0BQB', 'K8WHA')": [
        {
          "completed": false
        },
        {
          "turn": 1,
          "message": "K8WHA K0BQB EM17",
          "translated_message": "K0BQB sends a grid square location of EM17 to K8WHA.",
          "packet": {
            "snr": -16,
            "delta_time": 0.6000000238418579,
            "frequency_offset": 1302,
            "frequency": 14.075302,
            "band": "20m",
            "message": "K8WHA K0BQB EM17",
            "schema": 2,
            "program": "WSJT-X",
            "packet_type": 2
          },
          "type": "Grid Square Report"
        }
      ],
      "('KF0AX', 'VA2KFF')": [
        {
          "completed": false
        },
        {
          "turn": 1,
          "message": "KF0AX VA2KFF FN57",
          "translated_message": "VA2KFF sends a grid square location of FN57 to KF0AX.",
          "packet": {
            "snr": -19,
            "delta_time": 0.6000000238418579,
            "frequency_offset": 1322,
            "frequency": 14.075322,
            "band": "20m",
            "message": "KF0AX VA2KFF FN57",
            "schema": 2,
            "program": "WSJT-X",
            "packet_type": 2
          },
          "type": "Grid Square Report"
        }
      ],
      "('W5WNR', 'W9AV')": [
        {
          "completed": true
        },
        {
          "turn": 1,
          "message": "W5WNR W9AV EN43",
          "translated_message": "W9AV sends a grid square location of EN43 to W5WNR.",
          "packet": {
            "snr": -19,
            "delta_time": 0.6000000238418579,
            "frequency_offset": 1267,
            "frequency": 14.075267,
            "band": "20m",
            "message": "W5WNR W9AV EN43",
            "schema": 2,
            "program": "WSJT-X",
            "packet_type": 2
          },
          "type": "Grid Square Report"
        },
        {
          "turn": 2,
          "message": "W5WNR W9AV R-05",
          "translated_message": "W9AV says Roger and reports a signal report of -05 to W5WNR.",
          "packet": {
            "snr": -17,
            "delta_time": 0.6000000238418579,
            "frequency_offset": 1267,
            "frequency": 14.075267,
            "band": "20m",
            "message": "W5WNR W9AV R-05",
            "schema": 2,
            "program": "WSJT-X",
            "packet_type": 2
          },
          "type": "Signal Report"
        },
        {
          "turn": 3,
          "message": "W5WNR W9AV 73",
          "translated_message": "W9AV sends their well wishes to W5WNR, concluding the connection.",
          "packet": {
            "snr": -10,
            "delta_time": 0.6000000238418579,
            "frequency_offset": 1266,
            "frequency": 14.075266,
            "band": "20m",
            "message": "W5WNR W9AV 73",
            "schema": 2,
            "program": "WSJT-X",
            "packet_type": 2
          },
          "type": "Goodbye"
        }
      ],
      "('N1EDF', 'WA4BAY')": [
        {
          "completed": false
        },
        {
          "turn": 1,
          "message": "N1EDF WA4BAY -18",
          "translated_message": "WA4BAY sends signal report of -18 to N1EDF.",
          "packet": {
            "snr": -7,
            "delta_time": 0.5,
            "frequency_offset": 1322,
            "frequency": 14.075322,
            "band": "20m",
            "message": "N1EDF WA4BAY -18",
            "schema": 2,
            "program": "WSJT-X",
            "packet_type": 2
          },
          "type": "Signal Report"
        },
        {
          "turn": 2,
          "message": "N1EDF WA4BAY -18",
          "translated_message": "WA4BAY sends signal report of -18 to N1EDF.",
          "packet": {
            "snr": -10,
            "delta_time": 0.5,
            "frequency_offset": 1321,
            "frequency": 14.075321,
            "band": "20m",
            "message": "N1EDF WA4BAY -18",
            "schema": 2,
            "program": "WSJT-X",
            "packet_type": 2
          },
          "type": "Signal Report"
        },
        {
          "turn": 3,
          "message": "N1EDF WA4BAY -18",
          "translated_message": "WA4BAY sends signal report of -18 to N1EDF.",
          "packet": {
            "snr": -11,
            "delta_time": 0.5,
            "frequency_offset": 1321,
            "frequency": 14.075321,
            "band": "20m",
            "message": "N1EDF WA4BAY -18",
            "schema": 2,
            "program": "WSJT-X",
            "packet_type": 2
          },
          "type": "Signal Report"
        },
        {
          "turn": 4,
          "message": "N1EDF WA4BAY -18",
          "translated_message": "WA4BAY sends signal report of -18 to N1EDF.",
          "packet": {
            "snr": -22,
            "delta_time": 0.5,
            "frequency_offset": 1322,
            "frequency": 14.075322,
            "band": "20m",
            "message": "N1EDF WA4BAY -18",
            "schema": 2,
            "program": "WSJT-X",
            "packet_type": 2
          },
          "type": "Signal Report"
        }
      ],
      "('NS4P', 'VE3IBW')": [
        {
          "completed": false
        },
        {
          "turn": 1,
          "message": "VE3IBW NS4P EL87",
          "translated_message": "NS4P sends a grid square location of EL87 to VE3IBW.",
          "packet": {
            "snr": -8,
            "delta_time": 0.5,
            "frequency_offset": 984,
            "frequency": 14.074984,
            "band": "20m",
            "message": "VE3IBW NS4P EL87",
            "schema": 2,
            "program": "WSJT-X",
            "packet_type": 2
          },
          "type": "Grid Square Report"
        },
        {
          "turn": 2,
          "message": "VE3IBW NS4P EL87",
          "translated_message": "NS4P sends a grid square location of EL87 to VE3IBW.",
          "packet": {
            "snr": -12,
            "delta_time": 0.5,
            "frequency_offset": 983,
            "frequency": 14.074983,
            "band": "20m",
            "message": "VE3IBW NS4P EL87",
            "schema": 2,
            "program": "WSJT-X",
            "packet_type": 2
          },
          "type": "Grid Square Report"
        },
        {
          "turn": 3,
          "message": "VE3IBW NS4P R-18",
          "translated_message": "NS4P says Roger and reports a signal report of -18 to VE3IBW.",
          "packet": {
            "snr": -13,
            "delta_time": 0.5,
            "frequency_offset": 983,
            "frequency": 14.074983,
            "band": "20m",
            "message": "VE3IBW NS4P R-18",
            "schema": 2,
            "program": "WSJT-X",
            "packet_type": 2
          },
          "type": "Signal Report"
        },
        {
          "turn": 4,
          "message": "VE3IBW NS4P R-18",
          "translated_message": "NS4P says Roger and reports a signal report of -18 to VE3IBW.",
          "packet": {
            "snr": -13,
            "delta_time": 0.5,
            "frequency_offset": 984,
            "frequency": 14.074984,
            "band": "20m",
            "message": "VE3IBW NS4P R-18",
            "schema": 2,
            "program": "WSJT-X",
            "packet_type": 2
          },
          "type": "Signal Report"
        }
      ],
      "('K0VN', 'N6BO')": [
        {
          "completed": true
        },
        {
          "turn": 1,
          "message": "K0VN N6BO RR73",
          "translated_message": "N6BO sends a Roger Roger to K0VN and says goodbye, concluding the connection.",
          "packet": {
            "snr": -9,
            "delta_time": 0.6000000238418579,
            "frequency_offset": 1153,
            "frequency": 14.075153,
            "band": "20m",
            "message": "K0VN N6BO RR73",
            "schema": 2,
            "program": "WSJT-X",
            "packet_type": 2
          },
          "type": "RR & Goodbye"
        }
      ],
      "('N3KLJ', 'W8CO')": [
        {
          "completed": true
        },
        {
          "turn": 1,
          "message": "N3KLJ W8CO R-15",
          "translated_message": "W8CO says Roger and reports a signal report of -15 to N3KLJ.",
          "packet": {
            "snr": -12,
            "delta_time": 0.5,
            "frequency_offset": 518,
            "frequency": 14.074518,
            "band": "20m",
            "message": "N3KLJ W8CO R-15",
            "schema": 2,
            "program": "WSJT-X",
            "packet_type": 2
          },
          "type": "Signal Report"
        },
        {
          "turn": 2,
          "message": "N3KLJ W8CO 73",
          "translated_message": "W8CO sends their well wishes to N3KLJ, concluding the connection.",
          "packet": {
            "snr": -12,
            "delta_time": 0.5,
            "frequency_offset": 518,
            "frequency": 14.074518,
            "band": "20m",
            "message": "N3KLJ W8CO 73",
            "schema": 2,
            "program": "WSJT-X",
            "packet_type": 2
          },
          "type": "Goodbye"
        }
      ],
      "('AD9GE', 'W1KRB')": [
        {
          "completed": false
        },
        {
          "turn": 1,
          "message": "W1KRB AD9GE +05",
          "translated_message": "AD9GE sends signal report of +05 to W1KRB.",
          "packet": {
            "snr": -2,
            "delta_time": 0.5,
            "frequency_offset": 580,
            "frequency": 14.07458,
            "band": "20m",
            "message": "W1KRB AD9GE +05",
            "schema": 2,
            "program": "WSJT-X",
            "packet_type": 2
          },
          "type": "Signal Report"
        }
      ],
      "('N3KTU', 'W1WWB')": [
        {
          "completed": true
        },
        {
          "turn": 1,
          "message": "N3KTU W1WWB RR73",
          "translated_message": "W1WWB sends a Roger Roger to N3KTU and says goodbye, concluding the connection.",
          "packet": {
            "snr": -14,
            "delta_time": 1.0,
            "frequency_offset": 945,
            "frequency": 14.074945,
            "band": "20m",
            "message": "N3KTU W1WWB RR73",
            "schema": 2,
            "program": "WSJT-X",
            "packet_type": 2
          },
          "type": "RR & Goodbye"
        }
      ],
      "('KB0NG', 'KF5NQV')": [
        {
          "completed": false
        },
        {
          "turn": 1,
          "message": "KB0NG KF5NQV R-09",
          "translated_message": "KF5NQV says Roger and reports a signal report of -09 to KB0NG.",
          "packet": {
            "snr": -18,
            "delta_time": 1.2000000476837158,
            "frequency_offset": 1367,
            "frequency": 14.075367,
            "band": "20m",
            "message": "KB0NG KF5NQV R-09",
            "schema": 2,
            "program": "WSJT-X",
            "packet_type": 2
          },
          "type": "Signal Report"
        },
        {
          "turn": 2,
          "message": "KB0NG KF5NQV R-09",
          "translated_message": "KF5NQV says Roger and reports a signal report of -09 to KB0NG.",
          "packet": {
            "snr": -19,
            "delta_time": 1.2000000476837158,
            "frequency_offset": 1367,
            "frequency": 14.075367,
            "band": "20m",
            "message": "KB0NG KF5NQV R-09",
            "schema": 2,
            "program": "WSJT-X",
            "packet_type": 2
          },
          "type": "Signal Report"
        },
        {
          "turn": 3,
          "message": "KB0NG KF5NQV R-09",
          "translated_message": "KF5NQV says Roger and reports a signal report of -09 to KB0NG.",
          "packet": {
            "snr": -18,
            "delta_time": 1.2000000476837158,
            "frequency_offset": 1366,
            "frequency": 14.075366,
            "band": "20m",
            "message": "KB0NG KF5NQV R-09",
            "schema": 2,
            "program": "WSJT-X",
            "packet_type": 2
          },
          "type": "Signal Report"
        },
        {
          "turn": 4,
          "message": "KB0NG KF5NQV R-09",
          "translated_message": "KF5NQV says Roger and reports a signal report of -09 to KB0NG.",
          "packet": {
            "snr": -24,
            "delta_time": 1.2000000476837158,
            "frequency_offset": 1368,
            "frequency": 14.075368,
            "band": "20m",
            "message": "KB0NG KF5NQV R-09",
            "schema": 2,
            "program": "WSJT-X",
            "packet_type": 2
          },
          "type": "Signal Report"
        }
      ],
      "('DL1UDO', 'F4DVR')": [
        {
          "completed": false
        },
        {
          "turn": 1,
          "message": "F4DVR DL1UDO JO31",
          "translated_message": "DL1UDO sends a grid square location of JO31 to F4DVR.",
          "packet": {
            "snr": -16,
            "delta_time": 0.5,
            "frequency_offset": 1189,
            "frequency": 14.075189,
            "band": "20m",
            "message": "F4DVR DL1UDO JO31",
            "schema": 2,
            "program": "WSJT-X",
            "packet_type": 2
          },
          "type": "Grid Square Report"
        },
        {
          "turn": 2,
          "message": "F4DVR DL1UDO JO31",
          "translated_message": "DL1UDO sends a grid square location of JO31 to F4DVR.",
          "packet": {
            "snr": -21,
            "delta_time": 0.5,
            "frequency_offset": 1189,
            "frequency": 14.075189,
            "band": "20m",
            "message": "F4DVR DL1UDO JO31",
            "schema": 2,
            "program": "WSJT-X",
            "packet_type": 2
          },
          "type": "Grid Square Report"
        },
        {
          "turn": 3,
          "message": "F4DVR DL1UDO JO31",
          "translated_message": "DL1UDO sends a grid square location of JO31 to F4DVR.",
          "packet": {
            "snr": -23,
            "delta_time": 0.6000000238418579,
            "frequency_offset": 1188,
            "frequency": 14.075188,
            "band": "20m",
            "message": "F4DVR DL1UDO JO31",
            "schema": 2,
            "program": "WSJT-X",
            "packet_type": 2
          },
          "type": "Grid Square Report"
        }
      ],
      "('KE7RTB', 'N4FA')": [
        {
          "completed": false
        },
        {
          "turn": 1,
          "message": "N4FA KE7RTB R-21",
          "translated_message": "KE7RTB says Roger and reports a signal report of -21 to N4FA.",
          "packet": {
            "snr": -18,
            "delta_time": 0.800000011920929,
            "frequency_offset": 836,
            "frequency": 14.074836,
            "band": "20m",
            "message": "N4FA KE7RTB R-21",
            "schema": 2,
            "program": "WSJT-X",
            "packet_type": 2
          },
          "type": "Signal Report"
        }
      ],
      "('<...>', 'DL7ARV')": [
        {
          "completed": false
        },
        {
          "turn": 1,
          "message": "DL7ARV <...> -12",
          "translated_message": "<...> sends signal report of -12 to DL7ARV.",
          "packet": {
            "snr": -20,
            "delta_time": 0.4000000059604645,
            "frequency_offset": 1179,
            "frequency": 14.075179,
            "band": "20m",
            "message": "DL7ARV <...> -12",
            "schema": 2,
            "program": "WSJT-X",
            "packet_type": 2
          },
          "type": "Signal Report"
        }
      ],
      "('KB7GFL', 'VR2KW')": [
        {
          "completed": false
        },
        {
          "turn": 1,
          "message": "VR2KW KB7GFL CN97",
          "translated_message": "KB7GFL sends a grid square location of CN97 to VR2KW.",
          "packet": {
            "snr": -20,
            "delta_time": 0.6000000238418579,
            "frequency_offset": 1383,
            "frequency": 14.075383,
            "band": "20m",
            "message": "VR2KW KB7GFL CN97",
            "schema": 2,
            "program": "WSJT-X",
            "packet_type": 2
          },
          "type": "Grid Square Report"
        }
      ],
      "('KG4VUK', 'WA1KLI')": [
        {
          "completed": false
        },
        {
          "turn": 1,
          "message": "WA1KLI KG4VUK -10",
          "translated_message": "KG4VUK sends signal report of -10 to WA1KLI.",
          "packet": {
            "snr": -15,
            "delta_time": 0.5,
            "frequency_offset": 1337,
            "frequency": 14.075337,
            "band": "20m",
            "message": "WA1KLI KG4VUK -10",
            "schema": 2,
            "program": "WSJT-X",
            "packet_type": 2
          },
          "type": "Signal Report"
        }
      ],
      "('KC9GPS', 'NO4D')": [
        {
          "completed": false
        },
        {
          "turn": 1,
          "message": "KC9GPS NO4D EM84",
          "translated_message": "NO4D sends a grid square location of EM84 to KC9GPS.",
          "packet": {
            "snr": -14,
            "delta_time": 0.8999999761581421,
            "frequency_offset": 846,
            "frequency": 14.074845999999999,
            "band": "20m",
            "message": "KC9GPS NO4D EM84",
            "schema": 2,
            "program": "WSJT-X",
            "packet_type": 2
          },
          "type": "Grid Square Report"
        }
      ],
      "('G4IIY', 'K4MBU')": [
        {
          "completed": false
        },
        {
          "turn": 1,
          "message": "K4MBU G4IIY -14",
          "translated_message": "G4IIY sends signal report of -14 to K4MBU.",
          "packet": {
            "snr": -20,
            "delta_time": 0.5,
            "frequency_offset": 1019,
            "frequency": 14.075019,
            "band": "20m",
            "message": "K4MBU G4IIY -14",
            "schema": 2,
            "program": "WSJT-X",
            "packet_type": 2
          },
          "type": "Signal Report"
        },
        {
          "turn": 2,
          "message": "K4MBU G4IIY -12",
          "translated_message": "G4IIY sends signal report of -12 to K4MBU.",
          "packet": {
            "snr": -19,
            "delta_time": 0.5,
            "frequency_offset": 1019,
            "frequency": 14.075019,
            "band": "20m",
            "message": "K4MBU G4IIY -12",
            "schema": 2,
            "program": "WSJT-X",
            "packet_type": 2
          },
          "type": "Signal Report"
        },
        {
          "turn": 3,
          "message": "K4MBU G4IIY -13",
          "translated_message": "G4IIY sends signal report of -13 to K4MBU.",
          "packet": {
            "snr": -12,
            "delta_time": 0.5,
            "frequency_offset": 1018,
            "frequency": 14.075018,
            "band": "20m",
            "message": "K4MBU G4IIY -13",
            "schema": 2,
            "program": "WSJT-X",
            "packet_type": 2
          },
          "type": "Signal Report"
        }
      ],
      "('LY2VM', 'PA3DJP')": [
        {
          "completed": true
        },
        {
          "turn": 1,
          "message": "PA3DJP LY2VM -05",
          "translated_message": "LY2VM sends signal report of -05 to PA3DJP.",
          "packet": {
            "snr": -24,
            "delta_time": 0.6000000238418579,
            "frequency_offset": 243,
            "frequency": 14.074243,
            "band": "20m",
            "message": "PA3DJP LY2VM -05",
            "schema": 2,
            "program": "WSJT-X",
            "packet_type": 2
          },
          "type": "Signal Report"
        },
        {
          "turn": 2,
          "message": "PA3DJP LY2VM RR73",
          "translated_message": "LY2VM sends a Roger Roger to PA3DJP and says goodbye, concluding the connection.",
          "packet": {
            "snr": -20,
            "delta_time": 0.5,
            "frequency_offset": 243,
            "frequency": 14.074243,
            "band": "20m",
            "message": "PA3DJP LY2VM RR73",
            "schema": 2,
            "program": "WSJT-X",
            "packet_type": 2
          },
          "type": "RR & Goodbye"
        }
      ],
      "('N1UL', 'SQ6IMG')": [
        {
          "completed": false
        },
        {
          "turn": 1,
          "message": "CQ SQ6IMG JO80",
          "translated_message": "Station SQ6IMG is calling for any response from grid JO80.",
          "packet": {
            "snr": -17,
            "delta_time": 0.20000000298023224,
            "frequency_offset": 1238,
            "frequency": 14.075238,
            "band": "20m",
            "message": "CQ SQ6IMG JO80",
            "schema": 2,
            "program": "WSJT-X",
            "packet_type": 2
          },
          "type": "CQ Call."
        },
        {
          "turn": 2,
          "message": "SQ6IMG N1UL EL95",
          "translated_message": "N1UL sends a grid square location of EL95 to SQ6IMG.",
          "packet": {
            "snr": -22,
            "delta_time": 0.5,
            "frequency_offset": 1237,
            "frequency": 14.075237,
            "band": "20m",
            "message": "SQ6IMG N1UL EL95",
            "schema": 2,
            "program": "WSJT-X",
            "packet_type": 2
          },
          "type": "Grid Square Report"
        },
        {
          "turn": 3,
          "message": "SQ6IMG N1UL EL95",
          "translated_message": "N1UL sends a grid square location of EL95 to SQ6IMG.",
          "packet": {
            "snr": -11,
            "delta_time": 0.6000000238418579,
            "frequency_offset": 1238,
            "frequency": 14.075238,
            "band": "20m",
            "message": "SQ6IMG N1UL EL95",
            "schema": 2,
            "program": "WSJT-X",
            "packet_type": 2
          },
          "type": "Grid Square Report"
        }
      ],
      "('K5DZY', 'W7RTA')": [
        {
          "completed": false
        },
        {
          "turn": 1,
          "message": "W7RTA K5DZY -15",
          "translated_message": "K5DZY sends signal report of -15 to W7RTA.",
          "packet": {
            "snr": -19,
            "delta_time": 0.6000000238418579,
            "frequency_offset": 1193,
            "frequency": 14.075193,
            "band": "20m",
            "message": "W7RTA K5DZY -15",
            "schema": 2,
            "program": "WSJT-X",
            "packet_type": 2
          },
          "type": "Signal Report"
        },
        {
          "turn": 2,
          "message": "W7RTA K5DZY -15",
          "translated_message": "K5DZY sends signal report of -15 to W7RTA.",
          "packet": {
            "snr": -9,
            "delta_time": 0.6000000238418579,
            "frequency_offset": 1192,
            "frequency": 14.075192,
            "band": "20m",
            "message": "W7RTA K5DZY -15",
            "schema": 2,
            "program": "WSJT-X",
            "packet_type": 2
          },
          "type": "Signal Report"
        },
        {
          "turn": 3,
          "message": "W7RTA K5DZY -16",
          "translated_message": "K5DZY sends signal report of -16 to W7RTA.",
          "packet": {
            "snr": -8,
            "delta_time": 0.6000000238418579,
            "frequency_offset": 1193,
            "frequency": 14.075193,
            "band": "20m",
            "message": "W7RTA K5DZY -16",
            "schema": 2,
            "program": "WSJT-X",
            "packet_type": 2
          },
          "type": "Signal Report"
        }
      ],
      "('K9PWW', 'VA5KEN')": [
        {
          "completed": false
        },
        {
          "turn": 1,
          "message": "CQ VA5KEN DO70",
          "translated_message": "Station VA5KEN is calling for any response from grid DO70.",
          "packet": {
            "snr": -11,
            "delta_time": 0.6000000238418579,
            "frequency_offset": 631,
            "frequency": 14.074631,
            "band": "20m",
            "message": "CQ VA5KEN DO70",
            "schema": 2,
            "program": "WSJT-X",
            "packet_type": 2
          },
          "type": "CQ Call."
        },
        {
          "turn": 2,
          "message": "VA5KEN K9PWW EM57",
          "translated_message": "K9PWW sends a grid square location of EM57 to VA5KEN.",
          "packet": {
            "snr": -1,
            "delta_time": 0.5,
            "frequency_offset": 630,
            "frequency": 14.074629999999999,
            "band": "20m",
            "message": "VA5KEN K9PWW EM57",
            "schema": 2,
            "program": "WSJT-X",
            "packet_type": 2
          },
          "type": "Grid Square Report"
        },
        {
          "turn": 3,
          "message": "K9PWW VA5KEN -20",
          "translated_message": "VA5KEN sends signal report of -20 to K9PWW.",
          "packet": {
            "snr": -5,
            "delta_time": 0.6000000238418579,
            "frequency_offset": 631,
            "frequency": 14.074631,
            "band": "20m",
            "message": "K9PWW VA5KEN -20",
            "schema": 2,
            "program": "WSJT-X",
            "packet_type": 2
          },
          "type": "Signal Report"
        },
        {
          "turn": 4,
          "message": "VA5KEN K9PWW R+03",
          "translated_message": "K9PWW says Roger and reports a signal report of +03 to VA5KEN.",
          "packet": {
            "snr": -11,
            "delta_time": 0.5,
            "frequency_offset": 630,
            "frequency": 14.074629999999999,
            "band": "20m",
            "message": "VA5KEN K9PWW R+03",
            "schema": 2,
            "program": "WSJT-X",
            "packet_type": 2
          },
          "type": "Signal Report"
        },
        {
          "turn": 5,
          "message": "K9PWW VA5KEN -20",
          "translated_message": "VA5KEN sends signal report of -20 to K9PWW.",
          "packet": {
            "snr": -8,
            "delta_time": 0.6000000238418579,
            "frequency_offset": 630,
            "frequency": 14.074629999999999,
            "band": "20m",
            "message": "K9PWW VA5KEN -20",
            "schema": 2,
            "program": "WSJT-X",
            "packet_type": 2
          },
          "type": "Signal Report"
        },
        {
          "turn": 6,
          "message": "VA5KEN K9PWW R+03",
          "translated_message": "K9PWW says Roger and reports a signal report of +03 to VA5KEN.",
          "packet": {
            "snr": -20,
            "delta_time": 0.5,
            "frequency_offset": 631,
            "frequency": 14.074631,
            "band": "20m",
            "message": "VA5KEN K9PWW R+03",
            "schema": 2,
            "program": "WSJT-X",
            "packet_type": 2
          },
          "type": "Signal Report"
        }
      ],
      "('AF0E', 'KE8UKX')": [
        {
          "completed": true
        },
        {
          "turn": 1,
          "message": "KE8UKX AF0E +06",
          "translated_message": "AF0E sends signal report of +06 to KE8UKX.",
          "packet": {
            "snr": -7,
            "delta_time": 0.5,
            "frequency_offset": 1077,
            "frequency": 14.075077,
            "band": "20m",
            "message": "KE8UKX AF0E +06",
            "schema": 2,
            "program": "WSJT-X",
            "packet_type": 2
          },
          "type": "Signal Report"
        },
        {
          "turn": 2,
          "message": "KE8UKX AF0E RR73",
          "translated_message": "AF0E sends a Roger Roger to KE8UKX and says goodbye, concluding the connection.",
          "packet": {
            "snr": -9,
            "delta_time": 0.5,
            "frequency_offset": 1076,
            "frequency": 14.075076,
            "band": "20m",
            "message": "KE8UKX AF0E RR73",
            "schema": 2,
            "program": "WSJT-X",
            "packet_type": 2
          },
          "type": "RR & Goodbye"
        }
      ],
      "('KQ4COV', 'WW9W')": [
        {
          "completed": false
        },
        {
          "turn": 1,
          "message": "WW9W KQ4COV -18",
          "translated_message": "KQ4COV sends signal report of -18 to WW9W.",
          "packet": {
            "snr": -16,
            "delta_time": 0.5,
            "frequency_offset": 185,
            "frequency": 14.074185,
            "band": "20m",
            "message": "WW9W KQ4COV -18",
            "schema": 2,
            "program": "WSJT-X",
            "packet_type": 2
          },
          "type": "Signal Report"
        },
        {
          "turn": 2,
          "message": "WW9W KQ4COV -18",
          "translated_message": "KQ4COV sends signal report of -18 to WW9W.",
          "packet": {
            "snr": -24,
            "delta_time": 0.5,
            "frequency_offset": 184,
            "frequency": 14.074184,
            "band": "20m",
            "message": "WW9W KQ4COV -18",
            "schema": 2,
            "program": "WSJT-X",
            "packet_type": 2
          },
          "type": "Signal Report"
        }
      ],
      "('KN6PKG', 'VA5KEN')": [
        {
          "completed": false
        },
        {
          "turn": 1,
          "message": "VA5KEN KN6PKG DM13",
          "translated_message": "KN6PKG sends a grid square location of DM13 to VA5KEN.",
          "packet": {
            "snr": -19,
            "delta_time": 1.0,
            "frequency_offset": 469,
            "frequency": 14.074469,
            "band": "20m",
            "message": "VA5KEN KN6PKG DM13",
            "schema": 2,
            "program": "WSJT-X",
            "packet_type": 2
          },
          "type": "Grid Square Report"
        },
        {
          "turn": 2,
          "message": "VA5KEN KN6PKG DM13",
          "translated_message": "KN6PKG sends a grid square location of DM13 to VA5KEN.",
          "packet": {
            "snr": -20,
            "delta_time": 1.0,
            "frequency_offset": 470,
            "frequency": 14.07447,
            "band": "20m",
            "message": "VA5KEN KN6PKG DM13",
            "schema": 2,
            "program": "WSJT-X",
            "packet_type": 2
          },
          "type": "Grid Square Report"
        }
      ],
      "('N1PRR', 'N5VAN')": [
        {
          "completed": true
        },
        {
          "turn": 1,
          "message": "CQ N5VAN DN91",
          "translated_message": "Station N5VAN is calling for any response from grid DN91.",
          "packet": {
            "snr": -12,
            "delta_time": 0.4000000059604645,
            "frequency_offset": 577,
            "frequency": 14.074577,
            "band": "20m",
            "message": "CQ N5VAN DN91",
            "schema": 2,
            "program": "WSJT-X",
            "packet_type": 2
          },
          "type": "CQ Call."
        },
        {
          "turn": 1,
          "message": "CQ N1PRR DM33",
          "translated_message": "Station N1PRR is calling for any response from grid DM33.",
          "packet": {
            "snr": -15,
            "delta_time": 0.6000000238418579,
            "frequency_offset": 674,
            "frequency": 14.074674,
            "band": "20m",
            "message": "CQ N1PRR DM33",
            "schema": 2,
            "program": "WSJT-X",
            "packet_type": 2
          },
          "type": "CQ Call."
        },
        {
          "turn": 3,
          "message": "N5VAN N1PRR +04",
          "translated_message": "N1PRR sends signal report of +04 to N5VAN.",
          "packet": {
            "snr": -7,
            "delta_time": 0.699999988079071,
            "frequency_offset": 674,
            "frequency": 14.074674,
            "band": "20m",
            "message": "N5VAN N1PRR +04",
            "schema": 2,
            "program": "WSJT-X",
            "packet_type": 2
          },
          "type": "Signal Report"
        },
        {
          "turn": 4,
          "message": "N1PRR N5VAN R-13",
          "translated_message": "N5VAN says Roger and reports a signal report of -13 to N1PRR.",
          "packet": {
            "snr": -12,
            "delta_time": 0.4000000059604645,
            "frequency_offset": 576,
            "frequency": 14.074576,
            "band": "20m",
            "message": "N1PRR N5VAN R-13",
            "schema": 2,
            "program": "WSJT-X",
            "packet_type": 2
          },
          "type": "Signal Report"
        },
        {
          "turn": 5,
          "message": "N5VAN N1PRR RR73",
          "translated_message": "N1PRR sends a Roger Roger to N5VAN and says goodbye, concluding the connection.",
          "packet": {
            "snr": -17,
            "delta_time": 1.2000000476837158,
            "frequency_offset": 673,
            "frequency": 14.074673,
            "band": "20m",
            "message": "N5VAN N1PRR RR73",
            "schema": 2,
            "program": "WSJT-X",
            "packet_type": 2
          },
          "type": "RR & Goodbye"
        },
        {
          "turn": 6,
          "message": "N1PRR N5VAN RR73",
          "translated_message": "N5VAN sends a Roger Roger to N1PRR and says goodbye, concluding the connection.",
          "packet": {
            "snr": -5,
            "delta_time": 0.4000000059604645,
            "frequency_offset": 576,
            "frequency": 14.074576,
            "band": "20m",
            "message": "N1PRR N5VAN RR73",
            "schema": 2,
            "program": "WSJT-X",
            "packet_type": 2
          },
          "type": "RR & Goodbye"
        }
      ],
      "('AE0LB', 'VE3IBW')": [
        {
          "completed": false
        },
        {
          "turn": 1,
          "message": "VE3IBW AE0LB EM29",
          "translated_message": "AE0LB sends a grid square location of EM29 to VE3IBW.",
          "packet": {
            "snr": -14,
            "delta_time": 0.5,
            "frequency_offset": 581,
            "frequency": 14.074581,
            "band": "20m",
            "message": "VE3IBW AE0LB EM29",
            "schema": 2,
            "program": "WSJT-X",
            "packet_type": 2
          },
          "type": "Grid Square Report"
        }
      ],
      "('N2YBB', 'VO1IV')": [
        {
          "completed": false
        },
        {
          "turn": 1,
          "message": "CQ VO1IV GN37",
          "translated_message": "Station VO1IV is calling for any response from grid GN37.",
          "packet": {
            "snr": -9,
            "delta_time": 0.30000001192092896,
            "frequency_offset": 675,
            "frequency": 14.074675,
            "band": "20m",
            "message": "CQ VO1IV GN37",
            "schema": 2,
            "program": "WSJT-X",
            "packet_type": 2
          },
          "type": "CQ Call."
        },
        {
          "turn": 2,
          "message": "N2YBB VO1IV -22",
          "translated_message": "VO1IV sends signal report of -22 to N2YBB.",
          "packet": {
            "snr": -16,
            "delta_time": 0.30000001192092896,
            "frequency_offset": 675,
            "frequency": 14.074675,
            "band": "20m",
            "message": "N2YBB VO1IV -22",
            "schema": 2,
            "program": "WSJT-X",
            "packet_type": 2
          },
          "type": "Signal Report"
        }
      ],
      "('EI2KC', 'KG4VUK')": [
        {
          "completed": false
        },
        {
          "turn": 1,
          "message": "EI2KC KG4VUK EM64",
          "translated_message": "KG4VUK sends a grid square location of EM64 to EI2KC.",
          "packet": {
            "snr": -10,
            "delta_time": 0.5,
            "frequency_offset": 1337,
            "frequency": 14.075337,
            "band": "20m",
            "message": "EI2KC KG4VUK EM64",
            "schema": 2,
            "program": "WSJT-X",
            "packet_type": 2
          },
          "type": "Grid Square Report"
        },
        {
          "turn": 2,
          "message": "EI2KC KG4VUK EM64",
          "translated_message": "KG4VUK sends a grid square location of EM64 to EI2KC.",
          "packet": {
            "snr": -12,
            "delta_time": 0.5,
            "frequency_offset": 1337,
            "frequency": 14.075337,
            "band": "20m",
            "message": "EI2KC KG4VUK EM64",
            "schema": 2,
            "program": "WSJT-X",
            "packet_type": 2
          },
          "type": "Grid Square Report"
        }
      ],
      "('DK8HC/P', 'PD3LKN')": [
        {
          "completed": false
        },
        {
          "turn": 1,
          "message": "DK8HC/P PD3LKN JO22",
          "translated_message": "PD3LKN sends a grid square location of JO22 to DK8HC/P.",
          "packet": {
            "snr": -18,
            "delta_time": -0.10000000149011612,
            "frequency_offset": 431,
            "frequency": 14.074431,
            "band": "20m",
            "message": "DK8HC/P PD3LKN JO22",
            "schema": 2,
            "program": "WSJT-X",
            "packet_type": 2
          },
          "type": "Grid Square Report"
        }
      ],
      "('KK7MEH', 'W8ATE')": [
        {
          "completed": false
        },
        {
          "turn": 1,
          "message": "CQ W8ATE EN81",
          "translated_message": "Station W8ATE is calling for any response from grid EN81.",
          "packet": {
            "snr": 2,
            "delta_time": 0.6000000238418579,
            "frequency_offset": 817,
            "frequency": 14.074817,
            "band": "20m",
            "message": "CQ W8ATE EN81",
            "schema": 2,
            "program": "WSJT-X",
            "packet_type": 2
          },
          "type": "CQ Call."
        },
        {
          "turn": 2,
          "message": "KK7MEH W8ATE -11",
          "translated_message": "W8ATE sends signal report of -11 to KK7MEH.",
          "packet": {
            "snr": 5,
            "delta_time": 0.5,
            "frequency_offset": 816,
            "frequency": 14.074816,
            "band": "20m",
            "message": "KK7MEH W8ATE -11",
            "schema": 2,
            "program": "WSJT-X",
            "packet_type": 2
          },
          "type": "Signal Report"
        },
        {
          "turn": 3,
          "message": "KK7MEH W8ATE -11",
          "translated_message": "W8ATE sends signal report of -11 to KK7MEH.",
          "packet": {
            "snr": -3,
            "delta_time": 0.6000000238418579,
            "frequency_offset": 817,
            "frequency": 14.074817,
            "band": "20m",
            "message": "KK7MEH W8ATE -11",
            "schema": 2,
            "program": "WSJT-X",
            "packet_type": 2
          },
          "type": "Signal Report"
        }
      ],
      "('KI6HQT', 'W1WWB')": [
        {
          "completed": false
        },
        {
          "turn": 1,
          "message": "CQ W1WWB EM95",
          "translated_message": "Station W1WWB is calling for any response from grid EM95.",
          "packet": {
            "snr": -17,
            "delta_time": 1.0,
            "frequency_offset": 945,
            "frequency": 14.074945,
            "band": "20m",
            "message": "CQ W1WWB EM95",
            "schema": 2,
            "program": "WSJT-X",
            "packet_type": 2
          },
          "type": "CQ Call."
        },
        {
          "turn": 2,
          "message": "KI6HQT W1WWB +02",
          "translated_message": "W1WWB sends signal report of +02 to KI6HQT.",
          "packet": {
            "snr": -15,
            "delta_time": 1.0,
            "frequency_offset": 944,
            "frequency": 14.074944,
            "band": "20m",
            "message": "KI6HQT W1WWB +02",
            "schema": 2,
            "program": "WSJT-X",
            "packet_type": 2
          },
          "type": "Signal Report"
        }
      ],
      "('K0VN', 'W8CO')": [
        {
          "completed": true
        },
        {
          "turn": 1,
          "message": "K0VN W8CO -15",
          "translated_message": "W8CO sends signal report of -15 to K0VN.",
          "packet": {
            "snr": -19,
            "delta_time": 0.5,
            "frequency_offset": 517,
            "frequency": 14.074517,
            "band": "20m",
            "message": "K0VN W8CO -15",
            "schema": 2,
            "program": "WSJT-X",
            "packet_type": 2
          },
          "type": "Signal Report"
        },
        {
          "turn": 2,
          "message": "K0VN W8CO RR73",
          "translated_message": "W8CO sends a Roger Roger to K0VN and says goodbye, concluding the connection.",
          "packet": {
            "snr": -22,
            "delta_time": 0.5,
            "frequency_offset": 518,
            "frequency": 14.074518,
            "band": "20m",
            "message": "K0VN W8CO RR73",
            "schema": 2,
            "program": "WSJT-X",
            "packet_type": 2
          },
          "type": "RR & Goodbye"
        }
      ],
      "('K5MGY', 'N6BO')": [
        {
          "completed": false
        },
        {
          "turn": 1,
          "message": "K5MGY N6BO -07",
          "translated_message": "N6BO sends signal report of -07 to K5MGY.",
          "packet": {
            "snr": -20,
            "delta_time": 0.6000000238418579,
            "frequency_offset": 1138,
            "frequency": 14.075137999999999,
            "band": "20m",
            "message": "K5MGY N6BO -07",
            "schema": 2,
            "program": "WSJT-X",
            "packet_type": 2
          },
          "type": "Signal Report"
        }
      ],
      "('AA5SH', 'KZ4TU')": [
        {
          "completed": true
        },
        {
          "turn": 1,
          "message": "CQ KZ4TU EM90",
          "translated_message": "Station KZ4TU is calling for any response from grid EM90.",
          "packet": {
            "snr": -8,
            "delta_time": 0.5,
            "frequency_offset": 1030,
            "frequency": 14.07503,
            "band": "20m",
            "message": "CQ KZ4TU EM90",
            "schema": 2,
            "program": "WSJT-X",
            "packet_type": 2
          },
          "type": "CQ Call."
        },
        {
          "turn": 2,
          "message": "AA5SH KZ4TU +05",
          "translated_message": "KZ4TU sends signal report of +05 to AA5SH.",
          "packet": {
            "snr": -20,
            "delta_time": 0.6000000238418579,
            "frequency_offset": 1029,
            "frequency": 14.075029,
            "band": "20m",
            "message": "AA5SH KZ4TU +05",
            "schema": 2,
            "program": "WSJT-X",
            "packet_type": 2
          },
          "type": "Signal Report"
        },
        {
          "turn": 3,
          "message": "AA5SH KZ4TU RR73",
          "translated_message": "KZ4TU sends a Roger Roger to AA5SH and says goodbye, concluding the connection.",
          "packet": {
            "snr": -13,
            "delta_time": 0.5,
            "frequency_offset": 1030,
            "frequency": 14.07503,
            "band": "20m",
            "message": "AA5SH KZ4TU RR73",
            "schema": 2,
            "program": "WSJT-X",
            "packet_type": 2
          },
          "type": "RR & Goodbye"
        }
      ],
      "('N3KTU', 'WD5CFM')": [
        {
          "completed": false
        },
        {
          "turn": 1,
          "message": "CQ WD5CFM EL49",
          "translated_message": "Station WD5CFM is calling for any response from grid EL49.",
          "packet": {
            "snr": -14,
            "delta_time": 0.800000011920929,
            "frequency_offset": 911,
            "frequency": 14.074911,
            "band": "20m",
            "message": "CQ WD5CFM EL49",
            "schema": 2,
            "program": "WSJT-X",
            "packet_type": 2
          },
          "type": "CQ Call."
        },
        {
          "turn": 2,
          "message": "N3KTU WD5CFM -14",
          "translated_message": "WD5CFM sends signal report of -14 to N3KTU.",
          "packet": {
            "snr": -21,
            "delta_time": 0.800000011920929,
            "frequency_offset": 910,
            "frequency": 14.07491,
            "band": "20m",
            "message": "N3KTU WD5CFM -14",
            "schema": 2,
            "program": "WSJT-X",
            "packet_type": 2
          },
          "type": "Signal Report"
        },
        {
          "turn": 3,
          "message": "N3KTU WD5CFM -15",
          "translated_message": "WD5CFM sends signal report of -15 to N3KTU.",
          "packet": {
            "snr": -12,
            "delta_time": 0.800000011920929,
            "frequency_offset": 911,
            "frequency": 14.074911,
            "band": "20m",
            "message": "N3KTU WD5CFM -15",
            "schema": 2,
            "program": "WSJT-X",
            "packet_type": 2
          },
          "type": "Signal Report"
        }
      ],
      "('K4CAE', 'VE7LCG')": [
        {
          "completed": false
        },
        {
          "turn": 1,
          "message": "CQ K4CAE EM94",
          "translated_message": "Station K4CAE is calling for any response from grid EM94.",
          "packet": {
            "snr": -8,
            "delta_time": 0.6000000238418579,
            "frequency_offset": 1239,
            "frequency": 14.075239,
            "band": "20m",
            "message": "CQ K4CAE EM94",
            "schema": 2,
            "program": "WSJT-X",
            "packet_type": 2
          },
          "type": "CQ Call."
        },
        {
          "turn": 2,
          "message": "VE7LCG K4CAE -16",
          "translated_message": "K4CAE sends signal report of -16 to VE7LCG.",
          "packet": {
            "snr": 2,
            "delta_time": 0.6000000238418579,
            "frequency_offset": 1237,
            "frequency": 14.075237,
            "band": "20m",
            "message": "VE7LCG K4CAE -16",
            "schema": 2,
            "program": "WSJT-X",
            "packet_type": 2
          },
          "type": "Signal Report"
        }
      ],
      "('KD0JXE', 'NO4D')": [
        {
          "completed": false
        },
        {
          "turn": 1,
          "message": "KD0JXE NO4D EM84",
          "translated_message": "NO4D sends a grid square location of EM84 to KD0JXE.",
          "packet": {
            "snr": -5,
            "delta_time": 0.8999999761581421,
            "frequency_offset": 849,
            "frequency": 14.074849,
            "band": "20m",
            "message": "KD0JXE NO4D EM84",
            "schema": 2,
            "program": "WSJT-X",
            "packet_type": 2
          },
          "type": "Grid Square Report"
        }
      ],
      "('CU6AB', 'KE9AJC')": [
        {
          "completed": false
        },
        {
          "turn": 1,
          "message": "CU6AB KE9AJC EN61",
          "translated_message": "KE9AJC sends a grid square location of EN61 to CU6AB.",
          "packet": {
            "snr": -2,
            "delta_time": 0.699999988079071,
            "frequency_offset": 581,
            "frequency": 14.074581,
            "band": "20m",
            "message": "CU6AB KE9AJC EN61",
            "schema": 2,
            "program": "WSJT-X",
            "packet_type": 2
          },
          "type": "Grid Square Report"
        }
      ],
      "('N7DBS', 'VE7GYJ')": [
        {
          "completed": false
        },
        {
          "turn": 1,
          "message": "VE7GYJ N7DBS DM26",
          "translated_message": "N7DBS sends a grid square location of DM26 to VE7GYJ.",
          "packet": {
            "snr": -21,
            "delta_time": 0.6000000238418579,
            "frequency_offset": 1306,
            "frequency": 14.075306,
            "band": "20m",
            "message": "VE7GYJ N7DBS DM26",
            "schema": 2,
            "program": "WSJT-X",
            "packet_type": 2
          },
          "type": "Grid Square Report"
        }
      ],
      "('KN6PKG', 'WW6WWW')": [
        {
          "completed": false
        },
        {
          "turn": 1,
          "message": "CQ WW6WWW DN71",
          "translated_message": "Station WW6WWW is calling for any response from grid DN71.",
          "packet": {
            "snr": -18,
            "delta_time": 0.6000000238418579,
            "frequency_offset": 453,
            "frequency": 14.074453,
            "band": "20m",
            "message": "CQ WW6WWW DN71",
            "schema": 2,
            "program": "WSJT-X",
            "packet_type": 2
          },
          "type": "CQ Call."
        },
        {
          "turn": 2,
          "message": "WW6WWW KN6PKG DM13",
          "translated_message": "KN6PKG sends a grid square location of DM13 to WW6WWW.",
          "packet": {
            "snr": -24,
            "delta_time": 1.0,
            "frequency_offset": 470,
            "frequency": 14.07447,
            "band": "20m",
            "message": "WW6WWW KN6PKG DM13",
            "schema": 2,
            "program": "WSJT-X",
            "packet_type": 2
          },
          "type": "Grid Square Report"
        }
      ]
    }
  ],
  "CQS": [
    {
      "message": "CQ WA1CST EM76",
      "translated_message": "Station WA1CST is calling for any response from grid EM76.",
      "caller": "WA1CST",
      "packet": {
        "snr": -16,
        "delta_time": 0.6000000238418579,
        "frequency_offset": 165,
        "frequency": 14.074165,
        "band": "20m",
        "message": "CQ WA1CST EM76",
        "schema": 2,
        "program": "WSJT-X",
        "packet_type": 2
      }
    },
    {
      "message": "CQ KD2WRM FN21",
      "translated_message": "Station KD2WRM is calling for any response from grid FN21.",
      "caller": "KD2WRM",
      "packet": {
        "snr": -12,
        "delta_time": 0.5,
        "frequency_offset": 1044,
        "frequency": 14.075044,
        "band": "20m",
        "message": "CQ KD2WRM FN21",
        "schema": 2,
        "program": "WSJT-X",
        "packet_type": 2
      }
    },
    {
      "message": "CQ KE8ESJ EM79",
      "translated_message": "Station KE8ESJ is calling for any response from grid EM79.",
      "caller": "KE8ESJ",
      "packet": {
        "snr": -5,
        "delta_time": 0.5,
        "frequency_offset": 376,
        "frequency": 14.074375999999999,
        "band": "20m",
        "message": "CQ KE8ESJ EM79",
        "schema": 2,
        "program": "WSJT-X",
        "packet_type": 2
      }
    },
    {
      "message": "CQ K4TMR EM62",
      "translated_message": "Station K4TMR is calling for any response from grid EM62.",
      "caller": "K4TMR",
      "packet": {
        "snr": -15,
        "delta_time": 0.6000000238418579,
        "frequency_offset": 876,
        "frequency": 14.074876,
        "band": "20m",
        "message": "CQ K4TMR EM62",
        "schema": 2,
        "program": "WSJT-X",
        "packet_type": 2
      }
    },
    {
      "message": "CQ YO4GIY KN43",
      "translated_message": "Station YO4GIY is calling for any response from grid KN43.",
      "caller": "YO4GIY",
      "packet": {
        "snr": -20,
        "delta_time": 0.5,
        "frequency_offset": 1083,
        "frequency": 14.075083,
        "band": "20m",
        "message": "CQ YO4GIY KN43",
        "schema": 2,
        "program": "WSJT-X",
        "packet_type": 2
      }
    },
    {
      "message": "CQ N5VAN DN91",
      "translated_message": "Station N5VAN is calling for any response from grid DN91.",
      "caller": "N5VAN",
      "packet": {
        "snr": -8,
        "delta_time": 0.4000000059604645,
        "frequency_offset": 576,
        "frequency": 14.074576,
        "band": "20m",
        "message": "CQ N5VAN DN91",
        "schema": 2,
        "program": "WSJT-X",
        "packet_type": 2
      }
    },
    {
      "message": "CQ K4CAE EM94",
      "translated_message": "Station K4CAE is calling for any response from grid EM94.",
      "caller": "K4CAE",
      "packet": {
        "snr": -2,
        "delta_time": 0.6000000238418579,
        "frequency_offset": 1238,
        "frequency": 14.075238,
        "band": "20m",
        "message": "CQ K4CAE EM94",
        "schema": 2,
        "program": "WSJT-X",
        "packet_type": 2
      }
    },
    {
      "message": "CQ WA1CST EM76",
      "translated_message": "Station WA1CST is calling for any response from grid EM76.",
      "caller": "WA1CST",
      "packet": {
        "snr": -14,
        "delta_time": 0.6000000238418579,
        "frequency_offset": 165,
        "frequency": 14.074165,
        "band": "20m",
        "message": "CQ WA1CST EM76",
        "schema": 2,
        "program": "WSJT-X",
        "packet_type": 2
      }
    },
    {
      "message": "CQ KD2WRM FN21",
      "translated_message": "Station KD2WRM is calling for any response from grid FN21.",
      "caller": "KD2WRM",
      "packet": {
        "snr": -14,
        "delta_time": 0.5,
        "frequency_offset": 1044,
        "frequency": 14.075044,
        "band": "20m",
        "message": "CQ KD2WRM FN21",
        "schema": 2,
        "program": "WSJT-X",
        "packet_type": 2
      }
    },
    {
      "message": "CQ K9ZW EN64",
      "translated_message": "Station K9ZW is calling for any response from grid EN64.",
      "caller": "K9ZW",
      "packet": {
        "snr": -17,
        "delta_time": 0.699999988079071,
        "frequency_offset": 1189,
        "frequency": 14.075189,
        "band": "20m",
        "message": "CQ K9ZW EN64",
        "schema": 2,
        "program": "WSJT-X",
        "packet_type": 2
      }
    },
    {
      "message": "CQ KE8ESJ EM79",
      "translated_message": "Station KE8ESJ is calling for any response from grid EM79.",
      "caller": "KE8ESJ",
      "packet": {
        "snr": 0,
        "delta_time": 0.5,
        "frequency_offset": 376,
        "frequency": 14.074375999999999,
        "band": "20m",
        "message": "CQ KE8ESJ EM79",
        "schema": 2,
        "program": "WSJT-X",
        "packet_type": 2
      }
    },
    {
      "message": "CQ W8ATE EN81",
      "translated_message": "Station W8ATE is calling for any response from grid EN81.",
      "caller": "W8ATE",
      "packet": {
        "snr": -7,
        "delta_time": 0.6000000238418579,
        "frequency_offset": 817,
        "frequency": 14.074817,
        "band": "20m",
        "message": "CQ W8ATE EN81",
        "schema": 2,
        "program": "WSJT-X",
        "packet_type": 2
      }
    },
    {
      "message": "CQ K4TMR EM62",
      "translated_message": "Station K4TMR is calling for any response from grid EM62.",
      "caller": "K4TMR",
      "packet": {
        "snr": -22,
        "delta_time": 0.6000000238418579,
        "frequency_offset": 876,
        "frequency": 14.074876,
        "band": "20m",
        "message": "CQ K4TMR EM62",
        "schema": 2,
        "program": "WSJT-X",
        "packet_type": 2
      }
    },
    {
      "message": "CQ KF4ZGZ EM96",
      "translated_message": "Station KF4ZGZ is calling for any response from grid EM96.",
      "caller": "KF4ZGZ",
      "packet": {
        "snr": -10,
        "delta_time": 0.699999988079071,
        "frequency_offset": 1103,
        "frequency": 14.075103,
        "band": "20m",
        "message": "CQ KF4ZGZ EM96",
        "schema": 2,
        "program": "WSJT-X",
        "packet_type": 2
      }
    },
    {
      "message": "CQ YO4GIY KN43",
      "translated_message": "Station YO4GIY is calling for any response from grid KN43.",
      "caller": "YO4GIY",
      "packet": {
        "snr": -18,
        "delta_time": 0.5,
        "frequency_offset": 1083,
        "frequency": 14.075083,
        "band": "20m",
        "message": "CQ YO4GIY KN43",
        "schema": 2,
        "program": "WSJT-X",
        "packet_type": 2
      }
    },
    {
      "message": "CQ K4CAE EM94",
      "translated_message": "Station K4CAE is calling for any response from grid EM94.",
      "caller": "K4CAE",
      "packet": {
        "snr": -3,
        "delta_time": 0.6000000238418579,
        "frequency_offset": 1238,
        "frequency": 14.075238,
        "band": "20m",
        "message": "CQ K4CAE EM94",
        "schema": 2,
        "program": "WSJT-X",
        "packet_type": 2
      }
    },
    {
      "message": "CQ KD2WRM FN21",
      "translated_message": "Station KD2WRM is calling for any response from grid FN21.",
      "caller": "KD2WRM",
      "packet": {
        "snr": -8,
        "delta_time": 0.5,
        "frequency_offset": 1043,
        "frequency": 14.075042999999999,
        "band": "20m",
        "message": "CQ KD2WRM FN21",
        "schema": 2,
        "program": "WSJT-X",
        "packet_type": 2
      }
    },
    {
      "message": "CQ WA1CST EM76",
      "translated_message": "Station WA1CST is calling for any response from grid EM76.",
      "caller": "WA1CST",
      "packet": {
        "snr": -10,
        "delta_time": 0.6000000238418579,
        "frequency_offset": 165,
        "frequency": 14.074165,
        "band": "20m",
        "message": "CQ WA1CST EM76",
        "schema": 2,
        "program": "WSJT-X",
        "packet_type": 2
      }
    },
    {
      "message": "CQ K9ZW EN64",
      "translated_message": "Station K9ZW is calling for any response from grid EN64.",
      "caller": "K9ZW",
      "packet": {
        "snr": -16,
        "delta_time": 0.6000000238418579,
        "frequency_offset": 1187,
        "frequency": 14.075187,
        "band": "20m",
        "message": "CQ K9ZW EN64",
        "schema": 2,
        "program": "WSJT-X",
        "packet_type": 2
      }
    },
    {
      "message": "CQ KE8ESJ EM79",
      "translated_message": "Station KE8ESJ is calling for any response from grid EM79.",
      "caller": "KE8ESJ",
      "packet": {
        "snr": -8,
        "delta_time": 0.5,
        "frequency_offset": 375,
        "frequency": 14.074375,
        "band": "20m",
        "message": "CQ KE8ESJ EM79",
        "schema": 2,
        "program": "WSJT-X",
        "packet_type": 2
      }
    },
    {
      "message": "CQ YO4GIY KN43",
      "translated_message": "Station YO4GIY is calling for any response from grid KN43.",
      "caller": "YO4GIY",
      "packet": {
        "snr": -20,
        "delta_time": 0.5,
        "frequency_offset": 1083,
        "frequency": 14.075083,
        "band": "20m",
        "message": "CQ YO4GIY KN43",
        "schema": 2,
        "program": "WSJT-X",
        "packet_type": 2
      }
    },
    {
      "message": "CQ KF4ZGZ EM96",
      "translated_message": "Station KF4ZGZ is calling for any response from grid EM96.",
      "caller": "KF4ZGZ",
      "packet": {
        "snr": -23,
        "delta_time": 0.5,
        "frequency_offset": 1103,
        "frequency": 14.075103,
        "band": "20m",
        "message": "CQ KF4ZGZ EM96",
        "schema": 2,
        "program": "WSJT-X",
        "packet_type": 2
      }
    },
    {
      "message": "CQ WA1CST EM76",
      "translated_message": "Station WA1CST is calling for any response from grid EM76.",
      "caller": "WA1CST",
      "packet": {
        "snr": -6,
        "delta_time": 0.6000000238418579,
        "frequency_offset": 165,
        "frequency": 14.074165,
        "band": "20m",
        "message": "CQ WA1CST EM76",
        "schema": 2,
        "program": "WSJT-X",
        "packet_type": 2
      }
    },
    {
      "message": "CQ K9ZW EN64",
      "translated_message": "Station K9ZW is calling for any response from grid EN64.",
      "caller": "K9ZW",
      "packet": {
        "snr": -5,
        "delta_time": 0.6000000238418579,
        "frequency_offset": 1189,
        "frequency": 14.075189,
        "band": "20m",
        "message": "CQ K9ZW EN64",
        "schema": 2,
        "program": "WSJT-X",
        "packet_type": 2
      }
    },
    {
      "message": "CQ LY2VM KO14",
      "translated_message": "Station LY2VM is calling for any response from grid KO14.",
      "caller": "LY2VM",
      "packet": {
        "snr": -16,
        "delta_time": 0.5,
        "frequency_offset": 243,
        "frequency": 14.074243,
        "band": "20m",
        "message": "CQ LY2VM KO14",
        "schema": 2,
        "program": "WSJT-X",
        "packet_type": 2
      }
    },
    {
      "message": "CQ WW6WWW DN71",
      "translated_message": "Station WW6WWW is calling for any response from grid DN71.",
      "caller": "WW6WWW",
      "packet": {
        "snr": -18,
        "delta_time": 0.6000000238418579,
        "frequency_offset": 453,
        "frequency": 14.074453,
        "band": "20m",
        "message": "CQ WW6WWW DN71",
        "schema": 2,
        "program": "WSJT-X",
        "packet_type": 2
      }
    },
    {
      "message": "CQ KI4TAS EM75",
      "translated_message": "Station KI4TAS is calling for any response from grid EM75.",
      "caller": "KI4TAS",
      "packet": {
        "snr": -24,
        "delta_time": 0.5,
        "frequency_offset": 880,
        "frequency": 14.07488,
        "band": "20m",
        "message": "CQ KI4TAS EM75",
        "schema": 2,
        "program": "WSJT-X",
        "packet_type": 2
      }
    },
    {
      "message": "CQ KE8ESJ EM79",
      "translated_message": "Station KE8ESJ is calling for any response from grid EM79.",
      "caller": "KE8ESJ",
      "packet": {
        "snr": -11,
        "delta_time": 0.5,
        "frequency_offset": 376,
        "frequency": 14.074375999999999,
        "band": "20m",
        "message": "CQ KE8ESJ EM79",
        "schema": 2,
        "program": "WSJT-X",
        "packet_type": 2
      }
    },
    {
      "message": "CQ N6BO CM87",
      "translated_message": "Station N6BO is calling for any response from grid CM87.",
      "caller": "N6BO",
      "packet": {
        "snr": -19,
        "delta_time": 0.6000000238418579,
        "frequency_offset": 1140,
        "frequency": 14.07514,
        "band": "20m",
        "message": "CQ N6BO CM87",
        "schema": 2,
        "program": "WSJT-X",
        "packet_type": 2
      }
    }
  ],
  "MISC. COMMS": [
    {}
  ]
}